<annotation>
	<folder>bad</folder>
	<filename>bad.3dc9c41e-a659-11ec-afce-8c8590263dcc.jpg</filename>
	<path>/Users/albertsalgueda/Desktop/detection/assets/images/bad/bad.3dc9c41e-a659-11ec-afce-8c8590263dcc.jpg</path>
	<source>
		<database>Unknown</database>
	</source>
	<size>
		<width>1280</width>
		<height>720</height>
		<depth>3</depth>
	</size>
	<segmented>0</segmented>
	<object>
		<name>bad</name>
		<pose>Unspecified</pose>
		<truncated>0</truncated>
		<difficult>0</difficult>
		<bndbox>
			<xmin>283</xmin>
			<ymin>146</ymin>
			<xmax>488</xmax>
			<ymax>557</ymax>
		</bndbox>
	</object>
	<object>
		<name>CoolGuy</name>
		<pose>Unspecified</pose>
		<truncated>0</truncated>
		<difficult>0</difficult>
		<bndbox>
			<xmin>592</xmin>
			<ymin>124</ymin>
			<xmax>868</xmax>
			<ymax>468</ymax>
		</bndbox>
	</object>
</annotation>
